dbl_core/__init__.py
dbl_core/anchors.py
dbl_core/behavior/__init__.py
dbl_core/behavior/log.py
dbl_core/events/__init__.py
dbl_core/events/canonical.py
dbl_core/events/digest.py
dbl_core/events/errors.py
dbl_core/events/model.py
dbl_core/events/trace_digest.py
dbl_core/gate/__init__.py
dbl_core/gate/model.py
dbl_core/normalize/__init__.py
dbl_core/normalize/trace.py
dbl_core-0.3.6.dist-info/licenses/LICENSE
dbl_core-0.3.6.dist-info/METADATA
dbl_core-0.3.6.dist-info/WHEEL
dbl_core-0.3.6.dist-info/top_level.txt
dbl_core-0.3.6.dist-info/RECORD
