Metadata-Version: 2.4
Name: dbl-core
Version: 0.3.6
Summary: Deterministic Boundary Layers core substrate on KL Kernel Logic
Author-email: Lukas Pfister <228201683+lukaspfisterch@users.noreply.github.com>
License: MIT
Project-URL: Homepage, https://github.com/lukaspfisterch/dbl-core
Project-URL: Repository, https://github.com/lukaspfisterch/dbl-core
Project-URL: Issues, https://github.com/lukaspfisterch/dbl-core/issues
Keywords: dbl,deterministic,audit,event-log,governance
Classifier: Development Status :: 2 - Pre-Alpha
Classifier: Intended Audience :: Developers
Classifier: License :: OSI Approved :: MIT License
Classifier: Programming Language :: Python :: 3
Classifier: Programming Language :: Python :: 3.11
Classifier: Programming Language :: Python :: 3.12
Classifier: Typing :: Typed
Requires-Python: >=3.11
License-File: LICENSE
Requires-Dist: kl-kernel-logic<0.6.0,>=0.5.0
Provides-Extra: dev
Requires-Dist: pytest<9,>=8; extra == "dev"
Requires-Dist: ruff<1,>=0.5; extra == "dev"
Requires-Dist: mypy<2,>=1.10; extra == "dev"
Dynamic: license-file
